Workbook
Name Aporte: 'simulador '!$E$13
Name patrimonio: 'simulador '!$I$13
Name QTD_anos: 'simulador '!$I$10
Name Rendimento_carteira: 'simulador '!$E$11:$E$11
Name salario: 'simulador '!$E$10
Name sugestao_investimento: 'simulador '!$E$12
Name taxa_mensal: 'simulador '!$I$11

Sheet simulador 
B9: Dados Salariais Reais | G9: INVESTIMENTO MENSAL
B10: Salário | E10: 6000 | G10: Quantos anos investir | I10: 1
B11: Rendimento da carteira | E11: 0.0089 | G11: Taxa de rendimento mesal | I11: 0.01079
B12: Sugestão de investimentos | E12: 0.05 | G12: Investimento mensal | I12: =$E$13 -> 300 | M12: =$E$13 -> 300
B13: Aporte (valor a ser investido) | E13: =$E$12*$E$10 -> 300 | G13: Patrimônio acumulado | I13: =FV(taxa_mensal,QTD_anos*12,Aporte*-1) -> 3821.5158
G14: Dividendos Mesais | I14: {=patrimonio*Rendimento_carteira} -> 34.011491
B18: Simulações | H18: Perfil de investidor: | K18: Conservador
B19: Tempo de investimento (anos) | D19: Patrimônio | E19: Dividendos | F19: Investido | H19: Valor a ser investido por mês | K19: =Aporte -> 300
B20: 2 | D20: =FV(taxa_mensal,$B20*12,Aporte*-1) -> 8168.2882 | E20: {=D20*Rendimento_carteira} -> 72.697765 | F20: =$M$12*$B20*12 -> 7200
B21: 5 | D21: =FV(taxa_mensal,$B21*12,Aporte*-1) -> 25133.074 | E21: {=D21*Rendimento_carteira} -> 223.68436 | F21: =$M$12*$B21*12 -> 18000 | H21: Tipo de FII | J21: % sugerida | K21: Valores
B22: 10 | D22: =FV(taxa_mensal,$B22*12,Aporte*-1) -> 72985.264 | E22: {=D22*Rendimento_carteira} -> 649.56885 | F22: =$M$12*$B22*12 -> 36000 | H22: Papel | J22: =VLOOKUP($K$18&"-"&$H22,Planilha1!$A:$D,4,FALSE) -> 0.35 | K22: =J22*$K$19 -> 105
B23: 15 | D23: =FV(taxa_mensal,$B23*12,Aporte*-1) -> 164093.58 | E23: {=D23*Rendimento_carteira} -> 1460.4329 | F23: =$M$12*$B23*12 -> 54000 | H23: Tijolo | J23: =VLOOKUP($K$18&"-"&$H23,Planilha1!$A:$D,4,FALSE) -> 0.5 | K23: =J23*$K$19 -> 150
B24: 20 | D24: =FV(taxa_mensal,$B24*12,Aporte*-1) -> 337559.52 | E24: {=D24*Rendimento_carteira} -> 3004.2797 | F24: =$M$12*$B24*12 -> 72000 | H24: híbridos | J24: =VLOOKUP($K$18&"-"&$H24,Planilha1!$A:$D,4,FALSE) -> 0.075 | K24: =J24*$K$19 -> 22.5
B25: 25 | D25: =FV(taxa_mensal,$B25*12,Aporte*-1) -> 667830.5 | E25: {=D25*Rendimento_carteira} -> 5943.6915 | F25: =$M$12*$B25*12 -> 90000 | H25: FOFs | J25: =VLOOKUP($K$18&"-"&$H25,Planilha1!$A:$D,4,FALSE) -> 0.075 | K25: =J25*$K$19 -> 22.5
B26: 30 | D26: =FV(taxa_mensal,$B26*12,Aporte*-1) -> 1296650.9 | E26: {=D26*Rendimento_carteira} -> 11540.193 | F26: =$M$12*$B26*12 -> 108000 | H26: Desenvolvimento | J26: =VLOOKUP($K$18&"-"&$H26,Planilha1!$A:$D,4,FALSE) -> 0 | K26: =J26*$K$19 -> 0
B27: 35 | D27: =FV(taxa_mensal,$B27*12,Aporte*-1) -> 2493895.3 | E27: {=D27*Rendimento_carteira} -> 22195.668 | F27: =$M$12*$B27*12 -> 126000 | H27: Fiagro | J27: =VLOOKUP($K$18&"-"&$H27,Planilha1!$A:$D,4,FALSE) -> 0 | K27: =J27*$K$19 -> 0
H28: Total | K28: =SUM(K22:L27) -> 300

Sheet Planilha1
A3: Chave composta | B3: Perfil | C3: Tipo de FII | D3: % sugerida | F3: Anos | G3: Patrimônio | H3: Investido | I3: RSI
A4: =B4&"-"&C4 -> Conservador-Papel | B4: Conservador | C4: Papel | D4: 0.35 | F4: 2 | G4: ='simulador '!D20 -> 8168.2882 | H4: ='simulador '!F20 -> 7200 | I4: =G4/H4 -> 1.1344845
A5: =B5&"-"&C5 -> Conservador-Tijolo | B5: Conservador | C5: Tijolo | D5: 0.5 | F5: 5 | G5: ='simulador '!D21 -> 25133.074 | H5: ='simulador '!F21 -> 18000 | I5: =G5/H5 -> 1.3962819
A6: =B6&"-"&C6 -> Conservador-híbridos | B6: Conservador | C6: híbridos | D6: 0.075 | F6: 10 | G6: ='simulador '!D22 -> 72985.264 | H6: ='simulador '!F22 -> 36000 | I6: =G6/H6 -> 2.0273684
A7: =B7&"-"&C7 -> Conservador-FOFs | B7: Conservador | C7: FOFs | D7: 0.075 | F7: 15 | G7: ='simulador '!D23 -> 164093.58 | H7: ='simulador '!F23 -> 54000 | I7: =G7/H7 -> 3.03877
A8: =B8&"-"&C8 -> Conservador-Desenvolvimento | B8: Conservador | C8: Desenvolvimento | D8: 0 | F8: 20 | G8: ='simulador '!D24 -> 337559.52 | H8: ='simulador '!F24 -> 72000 | I8: =G8/H8 -> 4.6883267
A9: =B9&"-"&C9 -> Conservador-Fiagro | B9: Conservador | C9: Fiagro | D9: 0 | F9: 25 | G9: ='simulador '!D25 -> 667830.5 | H9: ='simulador '!F25 -> 90000 | I9: =G9/H9 -> 7.4203389
A10: =B10&"-"&C10 -> Moderado-Papel | B10: Moderado | C10: Papel | D10: 0.3 | F10: 30 | G10: ='simulador '!D26 -> 1296650.9 | H10: ='simulador '!F26 -> 108000 | I10: =G10/H10 -> 12.006027
A11: =B11&"-"&C11 -> Moderado-Tijolo | B11: Moderado | C11: Tijolo | D11: 0.3 | F11: 35 | G11: ='simulador '!D27 -> 2493895.3 | H11: ='simulador '!F27 -> 126000 | I11: =G11/H11 -> 19.79282
A12: =B12&"-"&C12 -> Moderado-híbridos | B12: Moderado | C12: híbridos | D12: 0.1
A13: =B13&"-"&C13 -> Moderado-FOFs | B13: Moderado | C13: FOFs | D13: 0.1
A14: =B14&"-"&C14 -> Moderado-Desenvolvimento | B14: Moderado | C14: Desenvolvimento | D14: 0.1
A15: =B15&"-"&C15 -> Moderado-Fiagro | B15: Moderado | C15: Fiagro | D15: 0.1
A16: =B16&"-"&C16 -> Agressivo-Papel | B16: Agressivo | C16: Papel | D16: 0.2
A17: =B17&"-"&C17 -> Agressivo-Tijolo | B17: Agressivo | C17: Tijolo | D17: 0.2
A18: =B18&"-"&C18 -> Agressivo-híbridos | B18: Agressivo | C18: híbridos | D18: 0.1
A19: =B19&"-"&C19 -> Agressivo-FOFs | B19: Agressivo | C19: FOFs | D19: 0.1
A20: =B20&"-"&C20 -> Agressivo-Desenvolvimento | B20: Agressivo | C20: Desenvolvimento | D20: 0.25
A21: =B21&"-"&C21 -> Agressivo-Fiagro | B21: Agressivo | C21: Fiagro | D21: 0.15
A22: =B22&"-"&C22 -> -
